mrp-eval
mrp-solver
mrpast/arginfer.py
mrpast/from_demes.py
mrpast/helpers.py
mrpast/main.py
mrpast/model.py
mrpast/polarize.py
mrpast/result.py
mrpast/simprocess.py
mrpast/simulate.py
mrpast-0.1.dist-info/METADATA
mrpast-0.1.dist-info/WHEEL
mrpast-0.1.dist-info/entry_points.txt
mrpast-0.1.dist-info/top_level.txt
mrpast-0.1.dist-info/RECORD
mrpast-0.1.dist-info/licenses/LICENSE
