Metadata-Version: 2.4
Name: mrpast
Version: 0.1
Summary: Demographic inference from Ancestral Recombination Graphs.
Home-page: https://aprilweilab.github.io/
Author: Drew DeHaas, April Wei
Author-email: 
Classifier: Programming Language :: Python :: 3
Classifier: Programming Language :: Python :: 3.9
Classifier: Programming Language :: Python :: 3.10
Classifier: Programming Language :: Python :: 3.11
Classifier: Programming Language :: Python :: 3.12
Classifier: Programming Language :: Python :: 3.13
Classifier: Operating System :: MacOS
Classifier: Operating System :: POSIX :: Linux
License-File: LICENSE
Requires-Dist: dataclasses_json
Requires-Dist: msprime
Requires-Dist: numpy
Requires-Dist: orjson
Requires-Dist: pandas
Requires-Dist: pyfaidx
Requires-Dist: pyyaml
Requires-Dist: tabulate
Requires-Dist: tqdm
Requires-Dist: tskit
Dynamic: author
Dynamic: classifier
Dynamic: description
Dynamic: description-content-type
Dynamic: home-page
Dynamic: license-file
Dynamic: requires-dist
Dynamic: summary
